LICENSE
MANIFEST.in
README.md
requirements.txt
setup.cfg
setup.py
geolens/__init__.py
geolens/geolens.py
geolens.egg-info/PKG-INFO
geolens.egg-info/SOURCES.txt
geolens.egg-info/dependency_links.txt
geolens.egg-info/not-zip-safe
geolens.egg-info/top_level.txt